alphafold/run_alphafold.py
alphafold/run_alphafold_test.py
alphafold/setup.py
alphafold/alphafold/__init__.py
alphafold/alphafold/version.py
alphafold/alphafold/common/__init__.py
alphafold/alphafold/common/confidence.py
alphafold/alphafold/common/confidence_test.py
alphafold/alphafold/common/mmcif_metadata.py
alphafold/alphafold/common/protein.py
alphafold/alphafold/common/protein_test.py
alphafold/alphafold/common/residue_constants.py
alphafold/alphafold/common/residue_constants_test.py
alphafold/alphafold/common/stereo_chemical_props.txt
alphafold/alphafold/data/__init__.py
alphafold/alphafold/data/feature_processing.py
alphafold/alphafold/data/mmcif_parsing.py
alphafold/alphafold/data/msa_identifiers.py
alphafold/alphafold/data/msa_pairing.py
alphafold/alphafold/data/parsers.py
alphafold/alphafold/data/pipeline.py
alphafold/alphafold/data/pipeline_multimer.py
alphafold/alphafold/data/templates.py
alphafold/alphafold/data/tools/__init__.py
alphafold/alphafold/data/tools/hhblits.py
alphafold/alphafold/data/tools/hhsearch.py
alphafold/alphafold/data/tools/hmmbuild.py
alphafold/alphafold/data/tools/hmmsearch.py
alphafold/alphafold/data/tools/jackhmmer.py
alphafold/alphafold/data/tools/kalign.py
alphafold/alphafold/data/tools/utils.py
alphafold/alphafold/model/__init__.py
alphafold/alphafold/model/all_atom.py
alphafold/alphafold/model/all_atom_multimer.py
alphafold/alphafold/model/all_atom_test.py
alphafold/alphafold/model/common_modules.py
alphafold/alphafold/model/config.py
alphafold/alphafold/model/data.py
alphafold/alphafold/model/features.py
alphafold/alphafold/model/folding.py
alphafold/alphafold/model/folding_multimer.py
alphafold/alphafold/model/layer_stack.py
alphafold/alphafold/model/layer_stack_test.py
alphafold/alphafold/model/lddt.py
alphafold/alphafold/model/lddt_test.py
alphafold/alphafold/model/mapping.py
alphafold/alphafold/model/model.py
alphafold/alphafold/model/modules.py
alphafold/alphafold/model/modules_multimer.py
alpharing-1.1.0.dist-info/METADATA
alpharing-1.1.0.dist-info/WHEEL
alpharing-1.1.0.dist-info/entry_points.txt
alpharing-1.1.0.dist-info/top_level.txt
alpharing-1.1.0.dist-info/RECORD
