Metadata-Version: 2.1
Name: alpharing
Version: 1.1.0
Summary: AlphaFold-based prediction of pathogenicity for any missense variant
Author-email: Aaron Logsdon <aaron.logsdon19@imperial.ac.uk>
License: GPLv3
Project-URL: Homepage, https://github.com/loggy01/alpharing
Classifier: Programming Language :: Python :: 3
Classifier: Operating System :: POSIX :: Linux
Requires-Python: ==3.10.*
Requires-Dist: absl-py ==1.0.0
Requires-Dist: biopython ==1.79
Requires-Dist: chex ==0.1.86
Requires-Dist: dm-haiku ==0.0.12
Requires-Dist: dm-tree ==0.1.8
Requires-Dist: immutabledict ==2.0.0
Requires-Dist: jax ==0.4.25
Requires-Dist: ml-collections ==0.1.0
Requires-Dist: numpy ==1.24.3
Requires-Dist: pandas ==2.0.3
Requires-Dist: scipy ==1.11.1
Requires-Dist: tensorflow-cpu ==2.16.1
